<?xml version = '1.0' encoding = 'UTF-8'?>
<Table class="oracle.dbtools.crest.model.design.relational.Table" id="E083BCD0-8306-0BFF-6648-DAF9A19A1D25" directorySegmentName="seg_1" name="CS_A_ANA_INDIRIZZO">
<sourceConnName>CS_F704-ROMA</sourceConnName>
<sourceObjSchema>CS_F704</sourceObjSchema>
<sourceObjName>CS_A_ANA_INDIRIZZO</sourceObjName>
<createdBy>Utente</createdBy>
<createdTime>2014-03-06 11:50:09 UTC</createdTime>
<generatorID>Generato dall&apos;utente</generatorID>
<ownerDesignName>CS</ownerDesignName>
<schemaObject>824E58FE-A577-697B-DF09-C944EBD934E9</schemaObject>
<pkName>CS_A_ANA_INDIRIZZO_PK</pkName>
<fonts>
<FontObject class="oracle.dbtools.crest.model.design.FontObjectWr">
<foType>Title</foType>
<fontSize>13</fontSize>
<fontStyle>1</fontStyle>
<colorRGB>-16776961</colorRGB>
</FontObject>
<FontObject class="oracle.dbtools.crest.model.design.FontObjectWr">
<foType>Column</foType>
<colorRGB>-16777216</colorRGB>
</FontObject>
<FontObject class="oracle.dbtools.crest.model.design.FontObjectWr">
<foType>Datatype</foType>
<colorRGB>-16744448</colorRGB>
</FontObject>
<FontObject class="oracle.dbtools.crest.model.design.FontObjectWr">
<foType>PK Element</foType>
<colorRGB>-16776961</colorRGB>
</FontObject>
<FontObject class="oracle.dbtools.crest.model.design.FontObjectWr">
<foType>FK Element</foType>
<colorRGB>-16777216</colorRGB>
</FontObject>
<FontObject class="oracle.dbtools.crest.model.design.FontObjectWr">
<foType>UK Element</foType>
<colorRGB>-16776961</colorRGB>
</FontObject>
<FontObject class="oracle.dbtools.crest.model.design.FontObjectWr">
<foType>Not Null</foType>
<colorRGB>-65536</colorRGB>
</FontObject>
<FontObject class="oracle.dbtools.crest.model.design.FontObjectWr">
<foType>Key</foType>
<colorRGB>-16777216</colorRGB>
</FontObject>
<FontObject class="oracle.dbtools.crest.model.design.FontObjectWr">
<foType>Titolo</foType>
<fontStyle>1</fontStyle>
<colorRGB>-16776961</colorRGB>
</FontObject>
<FontObject class="oracle.dbtools.crest.model.design.FontObjectWr">
<foType>Colonna</foType>
<colorRGB>-16777216</colorRGB>
</FontObject>
<FontObject class="oracle.dbtools.crest.model.design.FontObjectWr">
<foType>Tipo di dati</foType>
<colorRGB>-16744448</colorRGB>
</FontObject>
<FontObject class="oracle.dbtools.crest.model.design.FontObjectWr">
<foType>Elemento chiave privata</foType>
<colorRGB>-16776961</colorRGB>
</FontObject>
<FontObject class="oracle.dbtools.crest.model.design.FontObjectWr">
<foType>Elemento chiave esterna</foType>
<colorRGB>-16777216</colorRGB>
</FontObject>
<FontObject class="oracle.dbtools.crest.model.design.FontObjectWr">
<foType>Elemento chiave univoca</foType>
<colorRGB>-16776961</colorRGB>
</FontObject>
<FontObject class="oracle.dbtools.crest.model.design.FontObjectWr">
<foType>Non nullo</foType>
<colorRGB>-65536</colorRGB>
</FontObject>
<FontObject class="oracle.dbtools.crest.model.design.FontObjectWr">
<foType>Chiave</foType>
<colorRGB>-16777216</colorRGB>
</FontObject>
</fonts>
<columns>
<Column class="oracle.dbtools.crest.model.design.relational.Column" name="ID" id="1E0444EB-3808-54D1-6B30-2E150841CA40">
<sourceConnName>CS_F704-ROMA</sourceConnName>
<sourceObjSchema>CS_A_ANA_INDIRIZZO</sourceObjSchema>
<sourceObjName>ID</sourceObjName>
<createdBy>Utente</createdBy>
<createdTime>2014-03-06 11:50:31 UTC</createdTime>
<generatorID>Generato dall&apos;utente</generatorID>
<ownerDesignName>CS</ownerDesignName>
<useDomainConstraints>false</useDomainConstraints>
<use>1</use>
<logicalDatatype>LOGDT019</logicalDatatype>
<dataTypePrecision>10</dataTypePrecision>
<dataTypeScale>0</dataTypeScale>
<autoIncrementCycle>false</autoIncrementCycle>
</Column>
<Column class="oracle.dbtools.crest.model.design.relational.Column" name="CODICE_VIA" id="C742CE4A-E459-1397-30DF-9F461691EA62">
<sourceConnName>CS_F704-ROMA</sourceConnName>
<sourceObjSchema>CS_A_INDIRIZZO</sourceObjSchema>
<sourceObjName>CODICE_VIA</sourceObjName>
<createdBy>Utente</createdBy>
<createdTime>2014-03-06 11:50:31 UTC</createdTime>
<generatorID>Generato dall&apos;utente</generatorID>
<ownerDesignName>CS</ownerDesignName>
<nullsAllowed>true</nullsAllowed>
<useDomainConstraints>false</useDomainConstraints>
<use>1</use>
<logicalDatatype>LOGDT024</logicalDatatype>
<dataTypeSize>50 BYTE</dataTypeSize>
<autoIncrementCycle>false</autoIncrementCycle>
</Column>
<Column class="oracle.dbtools.crest.model.design.relational.Column" name="INDIRIZZO" id="3CBC8F55-47B5-DD34-9E01-1DD31B0D600D">
<sourceConnName>CS_F704-ROMA</sourceConnName>
<sourceObjSchema>CS_A_INDIRIZZO</sourceObjSchema>
<sourceObjName>INDIRIZZO</sourceObjName>
<createdBy>Utente</createdBy>
<createdTime>2014-03-06 11:50:31 UTC</createdTime>
<generatorID>Generato dall&apos;utente</generatorID>
<ownerDesignName>CS</ownerDesignName>
<nullsAllowed>true</nullsAllowed>
<useDomainConstraints>false</useDomainConstraints>
<use>1</use>
<logicalDatatype>LOGDT024</logicalDatatype>
<dataTypeSize>255 BYTE</dataTypeSize>
<autoIncrementCycle>false</autoIncrementCycle>
</Column>
<Column class="oracle.dbtools.crest.model.design.relational.Column" name="CIVICO_NUMERO" id="8439C0B9-661C-6CA9-11D3-B51C14C639D1">
<sourceConnName>CS_F704-ROMA</sourceConnName>
<sourceObjSchema>CS_A_INDIRIZZO</sourceObjSchema>
<sourceObjName>CIVICO_NUMERO</sourceObjName>
<createdBy>Utente</createdBy>
<createdTime>2014-03-06 11:50:31 UTC</createdTime>
<generatorID>Generato dall&apos;utente</generatorID>
<ownerDesignName>CS</ownerDesignName>
<nullsAllowed>true</nullsAllowed>
<useDomainConstraints>false</useDomainConstraints>
<use>1</use>
<logicalDatatype>LOGDT024</logicalDatatype>
<dataTypeSize>50 BYTE</dataTypeSize>
<autoIncrementCycle>false</autoIncrementCycle>
</Column>
<Column class="oracle.dbtools.crest.model.design.relational.Column" name="PROV" id="AF28CB5F-A276-D878-BB85-FB8188B80F2D">
<sourceConnName>CS_F704-ROMA</sourceConnName>
<sourceObjSchema>CS_A_INDIRIZZO</sourceObjSchema>
<sourceObjName>PROV</sourceObjName>
<createdBy>Utente</createdBy>
<createdTime>2014-03-06 11:50:31 UTC</createdTime>
<generatorID>Generato dall&apos;utente</generatorID>
<ownerDesignName>CS</ownerDesignName>
<nullsAllowed>true</nullsAllowed>
<useDomainConstraints>false</useDomainConstraints>
<use>1</use>
<logicalDatatype>LOGDT024</logicalDatatype>
<dataTypeSize>4 BYTE</dataTypeSize>
<autoIncrementCycle>false</autoIncrementCycle>
</Column>
<Column class="oracle.dbtools.crest.model.design.relational.Column" name="COM_COD" id="C0FC1479-CC4F-5D22-BB5A-7740B83CA177">
<sourceConnName>CS_F704-ROMA</sourceConnName>
<sourceObjSchema>CS_A_INDIRIZZO</sourceObjSchema>
<sourceObjName>COM_COD</sourceObjName>
<createdBy>Utente</createdBy>
<createdTime>2014-03-06 11:50:31 UTC</createdTime>
<generatorID>Generato dall&apos;utente</generatorID>
<ownerDesignName>CS</ownerDesignName>
<nullsAllowed>true</nullsAllowed>
<useDomainConstraints>false</useDomainConstraints>
<use>1</use>
<logicalDatatype>LOGDT024</logicalDatatype>
<dataTypeSize>30 BYTE</dataTypeSize>
<autoIncrementCycle>false</autoIncrementCycle>
</Column>
<Column class="oracle.dbtools.crest.model.design.relational.Column" name="COM_DES" id="5BB15173-C305-F8F1-D241-91A815B613CE">
<sourceConnName>CS_F704-ROMA</sourceConnName>
<sourceObjSchema>CS_A_INDIRIZZO</sourceObjSchema>
<sourceObjName>COM_DES</sourceObjName>
<createdBy>Utente</createdBy>
<createdTime>2014-03-06 11:50:31 UTC</createdTime>
<generatorID>Generato dall&apos;utente</generatorID>
<ownerDesignName>CS</ownerDesignName>
<nullsAllowed>true</nullsAllowed>
<useDomainConstraints>false</useDomainConstraints>
<use>1</use>
<logicalDatatype>LOGDT024</logicalDatatype>
<dataTypeSize>255 BYTE</dataTypeSize>
<autoIncrementCycle>false</autoIncrementCycle>
</Column>
<Column class="oracle.dbtools.crest.model.design.relational.Column" name="STATO_COD" id="7F487095-419E-F9AC-5744-F9A5F509A658">
<sourceConnName>CS_F704-ROMA</sourceConnName>
<sourceObjSchema>CS_A_INDIRIZZO</sourceObjSchema>
<sourceObjName>STATO_COD</sourceObjName>
<createdBy>Utente</createdBy>
<createdTime>2014-03-06 11:50:31 UTC</createdTime>
<generatorID>Generato dall&apos;utente</generatorID>
<ownerDesignName>CS</ownerDesignName>
<nullsAllowed>true</nullsAllowed>
<useDomainConstraints>false</useDomainConstraints>
<use>1</use>
<logicalDatatype>LOGDT024</logicalDatatype>
<dataTypeSize>30 BYTE</dataTypeSize>
<autoIncrementCycle>false</autoIncrementCycle>
</Column>
<Column class="oracle.dbtools.crest.model.design.relational.Column" name="STATO_DES" id="2D21D921-0BDE-B32B-8866-BFC31D60D5C6">
<sourceConnName>CS_F704-ROMA</sourceConnName>
<sourceObjSchema>CS_A_INDIRIZZO</sourceObjSchema>
<sourceObjName>STATO_DES</sourceObjName>
<createdBy>Utente</createdBy>
<createdTime>2014-03-06 11:50:31 UTC</createdTime>
<generatorID>Generato dall&apos;utente</generatorID>
<ownerDesignName>CS</ownerDesignName>
<nullsAllowed>true</nullsAllowed>
<useDomainConstraints>false</useDomainConstraints>
<use>1</use>
<logicalDatatype>LOGDT024</logicalDatatype>
<dataTypeSize>255 BYTE</dataTypeSize>
<autoIncrementCycle>false</autoIncrementCycle>
</Column>
<Column class="oracle.dbtools.crest.model.design.relational.Column" name="CIVICO_ALTRO" id="F4EDA73E-28A0-D7CA-BA1F-1CDA6A784D71">
<sourceConnName>CS_F704-ROMA</sourceConnName>
<sourceObjSchema>CS_A_INDIRIZZO</sourceObjSchema>
<sourceObjName>CIVICO_ALTRO</sourceObjName>
<createdBy>Utente</createdBy>
<createdTime>2014-03-06 11:50:31 UTC</createdTime>
<generatorID>Generato dall&apos;utente</generatorID>
<ownerDesignName>CS</ownerDesignName>
<nullsAllowed>true</nullsAllowed>
<useDomainConstraints>false</useDomainConstraints>
<use>1</use>
<logicalDatatype>LOGDT024</logicalDatatype>
<dataTypeSize>100 BYTE</dataTypeSize>
<autoIncrementCycle>false</autoIncrementCycle>
</Column>
</columns>
<indexes>
<ind_PK_UK class="oracle.dbtools.crest.model.design.relational.Index" id="A209529D-8D41-7EE3-99E2-517119EDD3FE" name="CS_A_ANA_INDIRIZZO_PK">
<sourceConnName>CS_F704-ROMA</sourceConnName>
<sourceObjSchema>CS_F704</sourceObjSchema>
<sourceObjName>CS_A_ANA_INDIRIZZO_PK</sourceObjName>
<createdBy>Utente</createdBy>
<createdTime>2014-03-06 11:50:31 UTC</createdTime>
<generatorID>Generato dall&apos;utente</generatorID>
<ownerDesignName>CS</ownerDesignName>
<pk>true</pk>
<indexState>Primary Constraint</indexState>
<indexColumnUsage>
<colUsage columnID="1E0444EB-3808-54D1-6B30-2E150841CA40"/>
</indexColumnUsage>
</ind_PK_UK>
<ind_PK_UK class="oracle.dbtools.crest.model.design.relational.Index" id="59890430-7CE8-6616-2C97-4FF14FDA7538" name="CS_A_ANA_INDIRIZZO_PK">
<sourceConnName>CS_F704-ROMA</sourceConnName>
<sourceObjSchema>CS_F704</sourceObjSchema>
<sourceObjName>CS_A_ANA_INDIRIZZO_PK</sourceObjName>
<createdBy>Utente</createdBy>
<createdTime>2014-03-06 14:07:49 UTC</createdTime>
<generatorID>Generato dall&apos;utente</generatorID>
<ownerDesignName>CS</ownerDesignName>
<importedID>9C03F504-3054-7BC4-2627-B7B96337BE9B</importedID>
<schemaObject>824E58FE-A577-697B-DF09-C944EBD934E9</schemaObject>
<indexState>Unique Plain Index</indexState>
<indexColumnUsage>
<colUsage columnID="1E0444EB-3808-54D1-6B30-2E150841CA40"/>
</indexColumnUsage>
</ind_PK_UK>
</indexes>
</Table>