<?xml version = '1.0' encoding = 'UTF-8'?>
<Table class="oracle.dbtools.crest.model.design.relational.Table" id="B83176AA-97F1-91F7-3715-A4E9FF56E546" directorySegmentName="seg_0" name="CS_I_SCHEDA_LAVORO">
<sourceConnName>CS_F704-ROMA</sourceConnName>
<sourceObjSchema>CS_F704</sourceObjSchema>
<sourceObjName>CS_I_SCHEDA_LAVORO</sourceObjName>
<createdBy>marcoultra</createdBy>
<createdTime>2014-09-16 07:06:08 UTC</createdTime>
<ownerDesignName>CS</ownerDesignName>
<importedID>544D2408-4270-6C31-45C7-FBC9BECD4B81</importedID>
<schemaObject>824E58FE-A577-697B-DF09-C944EBD934E9</schemaObject>
<pkName>CS_I_SCHEDA_LAVORO_PK</pkName>
<fonts>
<FontObject class="oracle.dbtools.crest.model.design.FontObjectWr">
<foType>Title</foType>
<fontStyle>1</fontStyle>
<colorRGB>-16776961</colorRGB>
</FontObject>
<FontObject class="oracle.dbtools.crest.model.design.FontObjectWr">
<foType>Column</foType>
<colorRGB>-16777216</colorRGB>
</FontObject>
<FontObject class="oracle.dbtools.crest.model.design.FontObjectWr">
<foType>Datatype</foType>
<colorRGB>-16744448</colorRGB>
</FontObject>
<FontObject class="oracle.dbtools.crest.model.design.FontObjectWr">
<foType>PK Element</foType>
<colorRGB>-16776961</colorRGB>
</FontObject>
<FontObject class="oracle.dbtools.crest.model.design.FontObjectWr">
<foType>FK Element</foType>
<colorRGB>-16777216</colorRGB>
</FontObject>
<FontObject class="oracle.dbtools.crest.model.design.FontObjectWr">
<foType>UK Element</foType>
<colorRGB>-16776961</colorRGB>
</FontObject>
<FontObject class="oracle.dbtools.crest.model.design.FontObjectWr">
<foType>Not Null</foType>
<colorRGB>-65536</colorRGB>
</FontObject>
<FontObject class="oracle.dbtools.crest.model.design.FontObjectWr">
<foType>Key</foType>
<colorRGB>-16777216</colorRGB>
</FontObject>
</fonts>
<columns>
<Column class="oracle.dbtools.crest.model.design.relational.Column" name="INTERVENTO_ID" id="579BFF21-53CC-5EE8-20A0-30A7B4465A6A">
<sourceConnName>CS_F704-ROMA</sourceConnName>
<sourceObjSchema>CS_I_SCHEDA_LAVORO</sourceObjSchema>
<sourceObjName>INTERVENTO_ID</sourceObjName>
<createdBy>marcoultra</createdBy>
<createdTime>2014-09-16 07:06:08 UTC</createdTime>
<ownerDesignName>CS</ownerDesignName>
<importedID>D6710204-7E6C-E0C5-60C9-9F6A87F1BAF8</importedID>
<useDomainConstraints>false</useDomainConstraints>
<use>1</use>
<logicalDatatype>LOGDT019</logicalDatatype>
<dataTypePrecision>10</dataTypePrecision>
<dataTypeScale>0</dataTypeScale>
<delegate>83F34D22-8E40-AED1-8DF4-1A10FB2AE938</delegate>
<autoIncrementCycle>false</autoIncrementCycle>
<associations>
<colAssociation fkAssociation="6E21D386-0BE2-C092-6D4D-05C3F80FE393" referredColumn="83F34D22-8E40-AED1-8DF4-1A10FB2AE938"/>
</associations>
</Column>
<Column class="oracle.dbtools.crest.model.design.relational.Column" name="COD_UTENTE" id="A03F15C1-7CBE-29F5-F5BF-88A6C970B5C5">
<sourceConnName>CS_F704-ROMA</sourceConnName>
<sourceObjSchema>CS_I_SCHEDA_LAVORO</sourceObjSchema>
<sourceObjName>COD_UTENTE</sourceObjName>
<createdBy>marcoultra</createdBy>
<createdTime>2014-09-16 07:06:08 UTC</createdTime>
<ownerDesignName>CS</ownerDesignName>
<importedID>C7E80718-AD7B-53BF-45CE-A815ED4BD49A</importedID>
<nullsAllowed>true</nullsAllowed>
<useDomainConstraints>false</useDomainConstraints>
<use>1</use>
<logicalDatatype>LOGDT024</logicalDatatype>
<dataTypeSize>50 BYTE</dataTypeSize>
<autoIncrementCycle>false</autoIncrementCycle>
</Column>
<Column class="oracle.dbtools.crest.model.design.relational.Column" name="ANNO" id="AA791EDA-E62D-4808-689F-B84947C79C04">
<sourceConnName>CS_F704-ROMA</sourceConnName>
<sourceObjSchema>CS_I_SCHEDA_LAVORO</sourceObjSchema>
<sourceObjName>ANNO</sourceObjName>
<createdBy>marcoultra</createdBy>
<createdTime>2014-09-16 07:06:08 UTC</createdTime>
<ownerDesignName>CS</ownerDesignName>
<importedID>E4CA29CC-F9F3-9592-5C6C-0E7A32132AF9</importedID>
<nullsAllowed>true</nullsAllowed>
<useDomainConstraints>false</useDomainConstraints>
<use>1</use>
<logicalDatatype>LOGDT019</logicalDatatype>
<dataTypePrecision>4</dataTypePrecision>
<autoIncrementCycle>false</autoIncrementCycle>
</Column>
<Column class="oracle.dbtools.crest.model.design.relational.Column" name="EDUCATORE_ID" id="2B82D74E-7BF5-824F-F2DE-573C760DDEB9">
<sourceConnName>CS_F704-ROMA</sourceConnName>
<sourceObjSchema>CS_I_SCHEDA_LAVORO</sourceObjSchema>
<sourceObjName>EDUCATORE_ID</sourceObjName>
<createdBy>marcoultra</createdBy>
<createdTime>2014-09-16 07:06:08 UTC</createdTime>
<ownerDesignName>CS</ownerDesignName>
<importedID>CB61FEBC-4915-762B-EDD8-AFB6004A8558</importedID>
<nullsAllowed>true</nullsAllowed>
<useDomainConstraints>false</useDomainConstraints>
<use>1</use>
<logicalDatatype>LOGDT019</logicalDatatype>
<dataTypePrecision>10</dataTypePrecision>
<autoIncrementCycle>false</autoIncrementCycle>
</Column>
<Column class="oracle.dbtools.crest.model.design.relational.Column" name="TIPO_CIRC4_ID" id="F00791B6-6EC1-AA69-CA60-517E088CF14B">
<sourceConnName>CS_F704-ROMA</sourceConnName>
<sourceObjSchema>CS_I_SCHEDA_LAVORO</sourceObjSchema>
<sourceObjName>TIPO_CIRC4_ID</sourceObjName>
<createdBy>marcoultra</createdBy>
<createdTime>2014-09-16 07:06:08 UTC</createdTime>
<ownerDesignName>CS</ownerDesignName>
<importedID>BEEB9DEA-DAE6-A01D-C5A4-F2C3297F1089</importedID>
<nullsAllowed>true</nullsAllowed>
<useDomainConstraints>false</useDomainConstraints>
<use>1</use>
<logicalDatatype>LOGDT019</logicalDatatype>
<dataTypePrecision>10</dataTypePrecision>
<autoIncrementCycle>false</autoIncrementCycle>
</Column>
<Column class="oracle.dbtools.crest.model.design.relational.Column" name="INTERVENTI_UOL_ID" id="F84DA771-07AD-1A97-CCDC-7E32ABA8C6F4">
<sourceConnName>CS_F704-ROMA</sourceConnName>
<sourceObjSchema>CS_I_SCHEDA_LAVORO</sourceObjSchema>
<sourceObjName>INTERVENTI_UOL_ID</sourceObjName>
<createdBy>marcoultra</createdBy>
<createdTime>2014-09-16 07:06:08 UTC</createdTime>
<ownerDesignName>CS</ownerDesignName>
<importedID>1F9D9E80-1888-9684-8E2D-E21DA998E575</importedID>
<nullsAllowed>true</nullsAllowed>
<useDomainConstraints>false</useDomainConstraints>
<use>1</use>
<logicalDatatype>LOGDT019</logicalDatatype>
<dataTypePrecision>10</dataTypePrecision>
<autoIncrementCycle>false</autoIncrementCycle>
</Column>
<Column class="oracle.dbtools.crest.model.design.relational.Column" name="TIPO_PROGETTO_ID" id="92981E0D-E5E4-C86E-BB70-E5FB2FA878B6">
<sourceConnName>CS_F704-ROMA</sourceConnName>
<sourceObjSchema>CS_I_SCHEDA_LAVORO</sourceObjSchema>
<sourceObjName>TIPO_PROGETTO_ID</sourceObjName>
<createdBy>marcoultra</createdBy>
<createdTime>2014-09-16 07:06:08 UTC</createdTime>
<ownerDesignName>CS</ownerDesignName>
<importedID>0B9AD7DA-78F8-57FE-2982-A3F0B575ED79</importedID>
<nullsAllowed>true</nullsAllowed>
<useDomainConstraints>false</useDomainConstraints>
<use>1</use>
<logicalDatatype>LOGDT019</logicalDatatype>
<dataTypePrecision>10</dataTypePrecision>
<autoIncrementCycle>false</autoIncrementCycle>
</Column>
<Column class="oracle.dbtools.crest.model.design.relational.Column" name="NOTE" id="AE9A3E7F-7F37-D7AF-E123-348CA7FDA0F8">
<sourceConnName>CS_F704-ROMA</sourceConnName>
<sourceObjSchema>CS_I_SCHEDA_LAVORO</sourceObjSchema>
<sourceObjName>NOTE</sourceObjName>
<createdBy>marcoultra</createdBy>
<createdTime>2014-09-16 07:06:08 UTC</createdTime>
<ownerDesignName>CS</ownerDesignName>
<importedID>15C7811A-6B3A-F640-603B-D54514426688</importedID>
<nullsAllowed>true</nullsAllowed>
<useDomainConstraints>false</useDomainConstraints>
<use>1</use>
<logicalDatatype>LOGDT024</logicalDatatype>
<dataTypeSize>4000 BYTE</dataTypeSize>
<autoIncrementCycle>false</autoIncrementCycle>
</Column>
</columns>
<indexes>
<ind_PK_UK class="oracle.dbtools.crest.model.design.relational.Index" id="BF639A00-3877-F799-0281-292C9BBDBCC5" name="CS_I_SCHEDA_LAVORO_PK">
<sourceConnName>CS_F704-ROMA</sourceConnName>
<sourceObjSchema>CS_F704</sourceObjSchema>
<sourceObjName>CS_I_SCHEDA_LAVORO_PK</sourceObjName>
<createdBy>marcoultra</createdBy>
<createdTime>2014-09-16 07:06:08 UTC</createdTime>
<ownerDesignName>CS</ownerDesignName>
<importedID>D515EB51-F6F2-9A14-784D-507DDDA4E84E</importedID>
<pk>true</pk>
<indexState>Primary Constraint</indexState>
<indexColumnUsage>
<colUsage columnID="579BFF21-53CC-5EE8-20A0-30A7B4465A6A"/>
</indexColumnUsage>
</ind_PK_UK>
<ind_PK_UK class="oracle.dbtools.crest.model.design.relational.Index" id="5D469BCA-8B77-3413-B686-D9A06E06076A" name="CS_I_SCHEDA_LAVORO_PK">
<sourceConnName>CS_F704-ROMA</sourceConnName>
<sourceObjSchema>CS_F704</sourceObjSchema>
<sourceObjName>CS_I_SCHEDA_LAVORO_PK</sourceObjName>
<createdBy>marcoultra</createdBy>
<createdTime>2014-09-16 07:06:08 UTC</createdTime>
<ownerDesignName>CS</ownerDesignName>
<importedID>6553E430-0E51-18F4-3F3F-EAFBCBA4088B</importedID>
<schemaObject>824E58FE-A577-697B-DF09-C944EBD934E9</schemaObject>
<indexState>Unique Plain Index</indexState>
<indexColumnUsage>
<colUsage columnID="579BFF21-53CC-5EE8-20A0-30A7B4465A6A"/>
</indexColumnUsage>
</ind_PK_UK>
<ind_PK_UK class="oracle.dbtools.crest.model.design.relational.Index" id="FC6D7144-A989-9581-E38E-53CB408E5FBA" name="CS_I_SCHEDALAV_INTER_FK">
<createdBy>marcoultra</createdBy>
<createdTime>2014-09-16 07:06:08 UTC</createdTime>
<generatorID>Generato dall&apos;utente</generatorID>
<ownerDesignName>CS</ownerDesignName>
<indexState>Foreign Key</indexState>
<indexColumnUsage>
<colUsage columnID="579BFF21-53CC-5EE8-20A0-30A7B4465A6A"/>
</indexColumnUsage>
</ind_PK_UK>
</indexes>
</Table>